asgiar/__init__.py
asgiar/contextlib.py
asgiar-0.2.1.dist-info/METADATA
asgiar-0.2.1.dist-info/WHEEL
asgiar-0.2.1.dist-info/top_level.txt
asgiar-0.2.1.dist-info/RECORD
